LICENSE
README.md
setup.cfg
setup.py
bones/kernel/bones.py
bones/kernel/explanations.py
bones/kernel/psm.py
bones/kernel/sym.py
bones/lang/core.py
bones/lang/execute.py
bones/lang/lex.py
bones/lang/parse_groups.py
bones/lang/parse_phrase.py
bones/lang/symbol_table.py
bones/lang/tc.py
bones_lang.egg-info/PKG-INFO
bones_lang.egg-info/SOURCES.txt
bones_lang.egg-info/dependency_links.txt
bones_lang.egg-info/not-zip-safe
bones_lang.egg-info/requires.txt
bones_lang.egg-info/top_level.txt