Metadata-Version: 2.4
Name: bones-lang
Version: 2025.5.1.1
Summary: Python implementation of the bones language
Home-page: https://github.com/coppertop-bones/bones
Download-URL: 
Author: David Briant
Author-email: dangermouseb@forwarding.cc
License: Apache
Keywords: multiple,dispatch,piping,pipeline,pipe,functional,multimethods,multidispatch,functools,lambda,curry,currying
Classifier: Development Status :: 3 - Alpha
Classifier: Intended Audience :: Developers
Classifier: Intended Audience :: End Users/Desktop
Classifier: Intended Audience :: Science/Research
Classifier: Topic :: Utilities
Classifier: License :: OSI Approved :: Apache Software License
Classifier: Programming Language :: Python :: 3.11
Requires-Python: >=3.11
License-File: LICENSE
Requires-Dist: coppertop-bones>=2025.05.01.1
Requires-Dist: numpy>=1.17.3
Dynamic: author
Dynamic: author-email
Dynamic: classifier
Dynamic: description
Dynamic: description-content-type
Dynamic: home-page
Dynamic: keywords
Dynamic: license
Dynamic: license-file
Dynamic: requires-dist
Dynamic: requires-python
Dynamic: summary
